validations_folder/Graph.py
validations_folder/JSON_Parser.py
validations_folder/Terminal.py
validations_folder/__init__.py
validations_folder/komponenta.py
validations_folder/validations.py
validations_folder-0.1.dist-info/LICENSE.txt
validations_folder-0.1.dist-info/METADATA
validations_folder-0.1.dist-info/WHEEL
validations_folder-0.1.dist-info/top_level.txt
validations_folder-0.1.dist-info/RECORD
