Metadata-Version: 2.1
Name: validations-folder
Version: 0.1
Summary: Validations For Schematic Editor Simple Graphs
Home-page: UNKNOWN
Author: Balsa Bulatovic
Author-email: baki.b.2k02@gmail.com
License: MIT
Platform: UNKNOWN
License-File: LICENSE.txt
